MANIFEST.in
setup.py
docs/INSTALL.txt
docs/api_example.py
docs/architecture.txt
docs/event_handlers.txt
mozmill/__init__.py
mozmill/handlers.py
mozmill/logger.py
mozmill/python_callbacks.py
mozmill/report.py
mozmill.egg-info/PKG-INFO
mozmill.egg-info/SOURCES.txt
mozmill.egg-info/dependency_links.txt
mozmill.egg-info/entry_points.txt
mozmill.egg-info/not-zip-safe
mozmill.egg-info/requires.txt
mozmill.egg-info/top_level.txt
mozmill/extension/chrome.manifest
mozmill/extension/install.rdf
mozmill/extension/META-INF/manifest.mf
mozmill/extension/META-INF/mozilla.rsa
mozmill/extension/META-INF/mozilla.sf
mozmill/extension/components/handlers.js
mozmill/extension/content/test/chrome_elements.xul
mozmill/extension/content/test/radio_buttons.xul
mozmill/extension/content/test/test.css
mozmill/extension/content/test/test.html
mozmill/extension/content/test/test.js
mozmill/extension/content/test/test.xul
mozmill/extension/resource/driver/controller.js
mozmill/extension/resource/driver/elementslib.js
mozmill/extension/resource/driver/mozelement.js
mozmill/extension/resource/driver/mozmill.js
mozmill/extension/resource/driver/msgbroker.js
mozmill/extension/resource/modules/assertions.js
mozmill/extension/resource/modules/driver.js
mozmill/extension/resource/modules/errors.js
mozmill/extension/resource/modules/frame.js
mozmill/extension/resource/modules/l10n.js
mozmill/extension/resource/modules/stack.js
mozmill/extension/resource/modules/windows.js
mozmill/extension/resource/stdlib/EventUtils.js
mozmill/extension/resource/stdlib/arrays.js
mozmill/extension/resource/stdlib/dom.js
mozmill/extension/resource/stdlib/httpd.js
mozmill/extension/resource/stdlib/json2.js
mozmill/extension/resource/stdlib/objects.js
mozmill/extension/resource/stdlib/os.js
mozmill/extension/resource/stdlib/securable-module.js
mozmill/extension/resource/stdlib/strings.js
mozmill/extension/resource/stdlib/utils.js
mozmill/extension/resource/stdlib/withs.js