Metadata-Version: 1.1
Name: mozmill
Version: 2.0.10.2
Summary: UI Automation tool for Mozilla applications
Home-page: http://github.com/mozilla/mozmill
Author: Mozilla Automation and Testing Team
Author-email: tools@lists.mozilla.org
License: http://www.mozilla.org/MPL/2.0/
Keywords: mozilla
Platform: UNKNOWN
Classifier: Environment :: Console
Classifier: Intended Audience :: Developers
Classifier: License :: OSI Approved :: Mozilla Public License 2.0 (MPL 2.0)
Classifier: Natural Language :: English
Classifier: Development Status :: 4 - Beta
Classifier: Operating System :: OS Independent
Classifier: Programming Language :: Python
Classifier: Topic :: Software Development :: Libraries :: Python Modules
